brick_cli/__init__.py
brick_cli/cli.py
brick_cli/commands/__init__.py
brick_cli/commands/create_project.py
brick_cli/commands/create_repository.py
brick_cli/commands/create_usecases.py
brick_cli/services.py
brick_cli/templates/abstract_repository.py.jinja2
brick_cli/templates/sqlalchemy_repository.py.jinja2
brick_cli/templates/usecases/abstract_usecase.py.jinja2
brick_cli/templates/usecases/create_usecase.py.jinja2
brick_cli/templates/usecases/delete_usecase.py.jinja2
brick_cli/templates/usecases/get_usecase.py.jinja2
brick_cli/templates/usecases/list_usecase.py.jinja2
brick_cli/templates/usecases/update_usecase.py.jinja2
brick_cli-0.1.1.dist-info/LICENSE
brick_cli-0.1.1.dist-info/METADATA
brick_cli-0.1.1.dist-info/WHEEL
brick_cli-0.1.1.dist-info/entry_points.txt
brick_cli-0.1.1.dist-info/RECORD
