Metadata-Version: 2.1
Name: brick-cli
Version: 0.1.1
Summary: CLI for clean architecture scaffolding
License: MIT
Author: Francisco
Author-email: vieirafrancisco.dev@gmail.com
Requires-Python: >=3.12,<4.0
Classifier: License :: OSI Approved :: MIT License
Classifier: Programming Language :: Python :: 3
Requires-Dist: click (>=8.1.8,<9.0.0)
Requires-Dist: jinja2 (>=3.1.5,<4.0.0)
